MANIFEST.in
README.rst
setup.cfg
setup.py
versioneer.py
dmpipe/__init__.py
dmpipe/_version.py
dmpipe/defaults.py
dmpipe/dm_collect.py
dmpipe/dm_plotting.py
dmpipe/dm_plotting_utils.py
dmpipe/dm_prepare.py
dmpipe/dm_spectral.py
dmpipe/dm_spectral_utils.py
dmpipe/dm_target.py
dmpipe/dmp_roi.py
dmpipe/lnl_norm_prior.py
dmpipe/name_policy.py
dmpipe/pipeline.py
dmpipe.egg-info/PKG-INFO
dmpipe.egg-info/SOURCES.txt
dmpipe.egg-info/dependency_links.txt
dmpipe.egg-info/entry_points.txt
dmpipe.egg-info/requires.txt
dmpipe.egg-info/top_level.txt
dmpipe/scripts/__init__.py
dmpipe/scripts/calc_sed_limits.py
dmpipe/scripts/extract_castro_data.py
dmpipe/scripts/extract_column_data.py
dmpipe/scripts/merge_maps.py
dmpipe/scripts/plot_catalog.py