Metadata-Version: 2.1
Name: dmpipe
Version: 0.1.3
Summary: Pipeline Scripts for LAT DM Analysis
Home-page: https://github.com/fermiPy/dmpipe
Author: Eric Charles
Author-email: echarles@slac.stanford.edu
License: BSD
Platform: UNKNOWN
Classifier: Intended Audience :: Science/Research
Classifier: License :: OSI Approved :: BSD License
Classifier: Operating System :: OS Independent
Classifier: Programming Language :: Python :: 2
Classifier: Programming Language :: Python :: 2.7
Classifier: Programming Language :: Python :: Implementation :: CPython
Classifier: Topic :: Scientific/Engineering :: Astronomy
Classifier: Development Status :: 4 - Beta
Provides-Extra: all
